commandintegrator/__init__.py
commandintegrator/commandintegrator.settings
commandintegrator/language.json
commandintegrator/baseclasses/__init__.py
commandintegrator/baseclasses/baseclasses.py
commandintegrator/core/__init__.py
commandintegrator/core/callback.py
commandintegrator/core/commandprocessor.py
commandintegrator/core/decorators.py
commandintegrator/core/enumerators.py
commandintegrator/core/internals.py
commandintegrator/core/interpretation.py
commandintegrator/core/pronounlookuptable.py
commandintegrator/models/__init__.py
commandintegrator/models/commandparser.py
commandintegrator/models/feature.py
commandintegrator/models/message.py
commandintegrator/tools/__init__.py
commandintegrator/tools/apihandles.py
commandintegrator/tools/pollcache.py
commandintegrator-1.3.0.data/data/config/commandintegrator.settings
commandintegrator-1.3.0.data/data/config/language.json
commandintegrator-1.3.0.dist-info/LICENSE
commandintegrator-1.3.0.dist-info/METADATA
commandintegrator-1.3.0.dist-info/WHEEL
commandintegrator-1.3.0.dist-info/top_level.txt
commandintegrator-1.3.0.dist-info/RECORD
