Metadata-Version: 2.1
Name: commandintegrator
Version: 1.3.0
Summary: A framework and API for developing chatbots and other command-driven applications
Home-page: https://github.com/dotchetter/commandintegrator
Author: Simon Olofsson
Author-email: dotchetter@protonmail.ch
License: UNKNOWN
Platform: UNKNOWN
Classifier: Programming Language :: Python :: 3
Classifier: License :: OSI Approved :: MIT License
Classifier: Operating System :: OS Independent
Requires-Python: >=3.8
Requires-Dist: pytz
Requires-Dist: requests
Requires-Dist: urllib3
